activedirectory/__init__.py
activedirectory/activedirectory.py
activedirectory/version.py
activedirectory-0.14.dist-info/DESCRIPTION.rst
activedirectory-0.14.dist-info/METADATA
activedirectory-0.14.dist-info/metadata.json
activedirectory-0.14.dist-info/RECORD
activedirectory-0.14.dist-info/top_level.txt
activedirectory-0.14.dist-info/WHEEL
