Metadata-Version: 2.0
Name: activedirectory
Version: 0.14
Summary: Easiest way to interact with ActiveDirectory / AD / LDAP Servers from Python, pure python approach.
Home-page: https://github.com/pycontribs/activedirectory
Author: Sorin Sbarnea
Author-email: sorin.sbarnea@gmail.com
License: Python
Download-URL: https://github.com/pycontribs/activedirectory/archives/master
Keywords: activedirectory,ad,ldap,ldap3
Platform: any
Classifier: Programming Language :: Python
Classifier: Programming Language :: Python :: 2.5
Classifier: Programming Language :: Python :: 2.6
Classifier: Programming Language :: Python :: 2.7
Classifier: Programming Language :: Python :: 3
Classifier: Development Status :: 4 - Beta
Classifier: Environment :: Other Environment
Classifier: Intended Audience :: Developers
Classifier: License :: OSI Approved :: BSD License
Classifier: Operating System :: OS Independent
Classifier: Topic :: Software Development :: Libraries :: Python Modules
Classifier: Topic :: Internet
Requires-Dist: six
Requires-Dist: ldap3
